__init__.py
ir_forecast/interest_rates.py
ir_forecast/ir_models.py
ir_forecast/monte_carlo.py
ir_forecast-0.0.1.dist-info/licenses/LICENSE
ir_forecast-0.0.1.dist-info/METADATA
ir_forecast-0.0.1.dist-info/WHEEL
ir_forecast-0.0.1.dist-info/top_level.txt
ir_forecast-0.0.1.dist-info/RECORD
