Metadata-Version: 2.4
Name: ir_forecast
Version: 0.0.1
Summary: Fetch historical Euribor data, initialize stochastic prediction models and forecast interest rates with Monte Carlo simulations.
Author-email: Niklas Pulliainen <niklas.pulliainen@gmail.com>
License-Expression: MIT
Project-URL: Homepage, https://github.com/Nikkex1/interest-rates
Project-URL: Issues, https://github.com/Nikkex1/interest-rates/issues
Classifier: Programming Language :: Python :: 3
Classifier: Operating System :: OS Independent
Requires-Python: >=3.12
License-File: LICENSE
Dynamic: license-file
